e164_python/__init__.py
e164_python/e164.py
e164_python/response.py
e164_python_sk-0.1.0.dist-info/LICENSE
e164_python_sk-0.1.0.dist-info/METADATA
e164_python_sk-0.1.0.dist-info/WHEEL
e164_python_sk-0.1.0.dist-info/top_level.txt
e164_python_sk-0.1.0.dist-info/RECORD
