Metadata-Version: 2.1
Name: e164-python-sk
Version: 0.1.0
Summary: A Python SDK package for accessing the e164.com phone number validation API.
Home-page: https://github.com/e164-com/e164-python
Author: Catalin Dragos
Author-email: catalin.dragos@e164.com
License: UNKNOWN
Platform: UNKNOWN
Classifier: Programming Language :: Python :: 3
Classifier: License :: OSI Approved :: MIT License
Classifier: Operating System :: OS Independent
Requires-Python: >=3.6
License-File: LICENSE
Requires-Dist: requests
